LICENSE
MANIFEST.in
README.md
requirements.txt
setup.cfg
setup.py
sgmarkets_plot/__init__.py
sgmarkets_plot/__meta__.py
sgmarkets_plot/_util.py
sgmarkets_plot/plot.py
sgmarkets_plot/sg_color.py
sgmarkets_plot/temp.py
sgmarkets_plot.egg-info/PKG-INFO
sgmarkets_plot.egg-info/SOURCES.txt
sgmarkets_plot.egg-info/dependency_links.txt
sgmarkets_plot.egg-info/not-zip-safe
sgmarkets_plot.egg-info/requires.txt
sgmarkets_plot.egg-info/top_level.txt