Metadata-Version: 1.1
Name: sgmarkets-plot
Version: 0.1.8
Summary: sgmarket api plot helper
Home-page: https://gitlab.com/sgmarkets/sgmarkets-plot
Author: sgmarkets
Author-email: olivier.borderies@gmail.com
License: MIT
Download-URL: https://gitlab.com/sgmarkets/sgmarkets-plot/repository/archive.tar.gz?ref=0.1.8
Keywords: sgmarkets,api,plotting,plot
Platform: UNKNOWN
Classifier: Development Status :: 4 - Beta
Classifier: License :: OSI Approved :: MIT License
Classifier: Programming Language :: Python :: 3.5
Classifier: Programming Language :: Python :: 3.6
